{
  "status": "Différée de 15 minutes",
  "items": [
    {
      "ticker": "ABJC",
      "price": "3 130",
      "variation": "7,38%"
    },
    {
      "ticker": "BICB",
      "price": "5 735",
      "variation": "2,86%"
    },
    {
      "ticker": "BICC",
      "price": "28 500",
      "variation": "-1,38%"
    },
    {
      "ticker": "BNBC",
      "price": "1 750",
      "variation": "7,36%"
    },
    {
      "ticker": "BOAB",
      "price": "8 745",
      "variation": "-1,09%"
    },
    {
      "ticker": "BOABF",
      "price": "5 500",
      "variation": "-0,80%"
    },
    {
      "ticker": "BOAC",
      "price": "8 890",
      "variation": "-0,45%"
    },
    {
      "ticker": "BOAM",
      "price": "4 630",
      "variation": "0,32%"
    },
    {
      "ticker": "BOAN",
      "price": "3 740",
      "variation": "0,00%"
    },
    {
      "ticker": "BOAS",
      "price": "7 400",
      "variation": "0,00%"
    },
    {
      "ticker": "CABC",
      "price": "4 050",
      "variation": "-0,62%"
    },
    {
      "ticker": "CBIBF",
      "price": "22 150",
      "variation": "2,33%"
    },
    {
      "ticker": "CFAC",
      "price": "1 575",
      "variation": "0,63%"
    },
    {
      "ticker": "CIEC",
      "price": "4 950",
      "variation": "-1,49%"
    },
    {
      "ticker": "ECOC",
      "price": "16 800",
      "variation": "0,00%"
    },
    {
      "ticker": "ETIT",
      "price": "33",
      "variation": "0,00%"
    },
    {
      "ticker": "FTSC",
      "price": "2 275",
      "variation": "0,44%"
    },
    {
      "ticker": "LNBB",
      "price": "3 835",
      "variation": "-0,13%"
    },
    {
      "ticker": "NEIC",
      "price": "1 960",
      "variation": "1,79%"
    },
    {
      "ticker": "NSBC",
      "price": "19 250",
      "variation": "-0,05%"
    },
    {
      "ticker": "NTLC",
      "price": "14 350",
      "variation": "2,64%"
    },
    {
      "ticker": "ONTBF",
      "price": "2 950",
      "variation": "1,36%"
    },
    {
      "ticker": "ORAC",
      "price": "15 800",
      "variation": "-0,31%"
    },
    {
      "ticker": "ORGT",
      "price": "2 790",
      "variation": "-0,90%"
    },
    {
      "ticker": "PALC",
      "price": "8 700",
      "variation": "0,17%"
    },
    {
      "ticker": "PRSC",
      "price": "4 250",
      "variation": "-1,18%"
    },
    {
      "ticker": "SAFC",
      "price": "3 700",
      "variation": "0,00%"
    },
    {
      "ticker": "SCRC",
      "price": "2 850",
      "variation": "1,40%"
    },
    {
      "ticker": "SDCC",
      "price": "12 000",
      "variation": "0,00%"
    },
    {
      "ticker": "SDSC",
      "price": "2 000",
      "variation": "-0,50%"
    },
    {
      "ticker": "SEMC",
      "price": "1 510",
      "variation": "-5,62%"
    },
    {
      "ticker": "SGBC",
      "price": "39 060",
      "variation": "0,00%"
    },
    {
      "ticker": "SHEC",
      "price": "2 075",
      "variation": "0,96%"
    },
    {
      "ticker": "SIBC",
      "price": "8 690",
      "variation": "2,12%"
    },
    {
      "ticker": "SICC",
      "price": "4 490",
      "variation": "0,11%"
    },
    {
      "ticker": "SIVC",
      "price": "2 840",
      "variation": "-0,88%"
    },
    {
      "ticker": "SLBC",
      "price": "38 900",
      "variation": "5,12%"
    },
    {
      "ticker": "SMBC",
      "price": "16 300",
      "variation": "7,48%"
    },
    {
      "ticker": "SNTS",
      "price": "28 420",
      "variation": "-0,60%"
    },
    {
      "ticker": "SOGC",
      "price": "8 200",
      "variation": "-2,24%"
    },
    {
      "ticker": "SPHC",
      "price": "7 525",
      "variation": "-0,66%"
    },
    {
      "ticker": "STAC",
      "price": "3 325",
      "variation": "7,22%"
    },
    {
      "ticker": "STBC",
      "price": "21 900",
      "variation": "-0,11%"
    },
    {
      "ticker": "TTLC",
      "price": "2 850",
      "variation": "-0,18%"
    },
    {
      "ticker": "TTLS",
      "price": "3 475",
      "variation": "-0,86%"
    },
    {
      "ticker": "UNLC",
      "price": "59 300",
      "variation": "0,08%"
    },
    {
      "ticker": "UNXC",
      "price": "1 945",
      "variation": "1,05%"
    }
  ]
}