{
  "status": "Différée de 15 minutes",
  "items": [
    {
      "ticker": "ABJC",
      "price": "3 435",
      "variation": "-6,61%"
    },
    {
      "ticker": "BICB",
      "price": "5 195",
      "variation": "0,10%"
    },
    {
      "ticker": "BICC",
      "price": "24 900",
      "variation": "-1,61%"
    },
    {
      "ticker": "BNBC",
      "price": "1 580",
      "variation": "-1,85%"
    },
    {
      "ticker": "BOAB",
      "price": "6 935",
      "variation": "0,94%"
    },
    {
      "ticker": "BOABF",
      "price": "4 785",
      "variation": "-1,78%"
    },
    {
      "ticker": "BOAC",
      "price": "8 090",
      "variation": "2,41%"
    },
    {
      "ticker": "BOAM",
      "price": "4 620",
      "variation": "4,10%"
    },
    {
      "ticker": "BOAN",
      "price": "2 850",
      "variation": "-2,06%"
    },
    {
      "ticker": "BOAS",
      "price": "7 000",
      "variation": "6,06%"
    },
    {
      "ticker": "CABC",
      "price": "3 820",
      "variation": "0,79%"
    },
    {
      "ticker": "CBIBF",
      "price": "14 100",
      "variation": "0,00%"
    },
    {
      "ticker": "CFAC",
      "price": "1 785",
      "variation": "-1,12%"
    },
    {
      "ticker": "CIEC",
      "price": "3 420",
      "variation": "7,36%"
    },
    {
      "ticker": "ECOC",
      "price": "17 000",
      "variation": "-0,09%"
    },
    {
      "ticker": "ETIT",
      "price": "32",
      "variation": "3,23%"
    },
    {
      "ticker": "FTSC",
      "price": "2 395",
      "variation": "0,21%"
    },
    {
      "ticker": "LNBB",
      "price": "3 895",
      "variation": "0,00%"
    },
    {
      "ticker": "NEIC",
      "price": "1 450",
      "variation": "0,69%"
    },
    {
      "ticker": "NSBC",
      "price": "14 700",
      "variation": "0,24%"
    },
    {
      "ticker": "NTLC",
      "price": "12 505",
      "variation": "-0,84%"
    },
    {
      "ticker": "ONTBF",
      "price": "2 895",
      "variation": "3,76%"
    },
    {
      "ticker": "ORAC",
      "price": "15 555",
      "variation": "0,29%"
    },
    {
      "ticker": "ORGT",
      "price": "3 300",
      "variation": "0,00%"
    },
    {
      "ticker": "PALC",
      "price": "9 050",
      "variation": "0,55%"
    },
    {
      "ticker": "PRSC",
      "price": "4 890",
      "variation": "7,47%"
    },
    {
      "ticker": "SAFC",
      "price": "5 795",
      "variation": "-3,42%"
    },
    {
      "ticker": "SCRC",
      "price": "1 600",
      "variation": "-3,03%"
    },
    {
      "ticker": "SDCC",
      "price": "7 490",
      "variation": "-1,76%"
    },
    {
      "ticker": "SDSC",
      "price": "2 150",
      "variation": "-0,46%"
    },
    {
      "ticker": "SEMC",
      "price": "2 230",
      "variation": "-4,73%"
    },
    {
      "ticker": "SGBC",
      "price": "37 450",
      "variation": "-1,20%"
    },
    {
      "ticker": "SHEC",
      "price": "2 175",
      "variation": "7,41%"
    },
    {
      "ticker": "SIBC",
      "price": "6 800",
      "variation": "-1,81%"
    },
    {
      "ticker": "SICC",
      "price": "4 300",
      "variation": "0,00%"
    },
    {
      "ticker": "SIVC",
      "price": "2 900",
      "variation": "-3,33%"
    },
    {
      "ticker": "SLBC",
      "price": "44 505",
      "variation": "0,98%"
    },
    {
      "ticker": "SMBC",
      "price": "13 400",
      "variation": "-0,04%"
    },
    {
      "ticker": "SNTS",
      "price": "29 300",
      "variation": "-0,99%"
    },
    {
      "ticker": "SOGC",
      "price": "8 725",
      "variation": "1,43%"
    },
    {
      "ticker": "SPHC",
      "price": "8 400",
      "variation": "1,13%"
    },
    {
      "ticker": "STAC",
      "price": "1 910",
      "variation": "-4,02%"
    },
    {
      "ticker": "STBC",
      "price": "21 475",
      "variation": "-0,12%"
    },
    {
      "ticker": "TTLC",
      "price": "3 000",
      "variation": "7,14%"
    },
    {
      "ticker": "TTLS",
      "price": "3 065",
      "variation": "7,39%"
    },
    {
      "ticker": "UNLC",
      "price": "70 010",
      "variation": "-5,77%"
    },
    {
      "ticker": "UNXC",
      "price": "2 305",
      "variation": "-2,12%"
    }
  ]
}